gd_vae_pytorch/__init__.py
gd_vae_pytorch/geo_map.py
gd_vae_pytorch/log.py
gd_vae_pytorch/nn.py
gd_vae_pytorch/utils.py
gd_vae_pytorch/vae.py
gd_vae_pytorch/tests/__init__.py
gd_vae_pytorch/tests/t1.py
gd_vae_pytorch-1.0.4.dist-info/LICENSE.txt
gd_vae_pytorch-1.0.4.dist-info/METADATA
gd_vae_pytorch-1.0.4.dist-info/WHEEL
gd_vae_pytorch-1.0.4.dist-info/top_level.txt
gd_vae_pytorch-1.0.4.dist-info/RECORD
