Metadata-Version: 2.1
Name: gd-vae-pytorch
Version: 1.0.4
Summary: Geometric Dynamic Variational Autoencoders (GD-VAEs).
Home-page: http://atzberger.org/
Author: Ryan Lopez and Paul J. Atzberger
Author-email: atzberg@gmail.com
Classifier: Programming Language :: Python :: 3
Classifier: License :: OSI Approved :: GNU General Public License v2 (GPLv2)
Classifier: Operating System :: OS Independent
Requires-Python: >=3.6
License-File: LICENSE.txt
